{"match_details":{"batting_first":"Kolkata Knight Riders","batting_second":"Royal Challengers Bangalore","venue":"M Chinnaswamy Stadium, Bengaluru, Bangalore","date":"26th April, 2023","winner":"Kolkata Knight Riders"},"players":[{"player_name":"Jason Roy","dismissal":"b Vijaykumar Vyshak","runs_scored":56,"balls_faced":29,"fours":4,"sixes":5,"strike_rate":193.1,"percent_runs":"28.00%","overs":null,"maidens":null,"runs_given":null,"wickets_taken":null,"economy":null,"percent_wickets":null,"catches":0,"opponent":"Royal Challengers Bangalore"},{"player_name":"Narayan Jagadeesan","dismissal":"c Willey b Vijaykumar Vyshak","runs_scored":27,"balls_faced":29,"fours":4,"sixes":0,"strike_rate":93.1,"percent_runs":"13.50%","overs":null,"maidens":null,"runs_given":null,"wickets_taken":null,"economy":null,"percent_wickets":null,"catches":0,"opponent":"Royal Challengers Bangalore"},{"player_name":"Venkatesh Iyer","dismissal":"c Maxwell b Wanindu Hasaranga","runs_scored":31,"balls_faced":26,"fours":3,"sixes":0,"strike_rate":119.23,"percent_runs":"15.50%","overs":null,"maidens":null,"runs_given":null,"wickets_taken":null,"economy":null,"percent_wickets":null,"catches":1,"opponent":"Royal Challengers Bangalore"},{"player_name":"Rinku Singh","dismissal":"not out","runs_scored":18,"balls_faced":10,"fours":2,"sixes":1,"strike_rate":180,"percent_runs":"9.00%","overs":null,"maidens":null,"runs_given":null,"wickets_taken":null,"economy":null,"percent_wickets":null,"catches":2,"opponent":"Royal Challengers Bangalore"},{"player_name":"David Wiese","dismissal":"not out","runs_scored":12,"balls_faced":3,"fours":0,"sixes":2,"strike_rate":400,"percent_runs":"6.00%","overs":null,"maidens":null,"runs_given":null,"wickets_taken":null,"economy":null,"percent_wickets":null,"catches":1,"opponent":"Royal Challengers Bangalore"},{"player_name":"Mohammed Siraj","dismissal":null,"runs_scored":null,"balls_faced":null,"fours":null,"sixes":null,"strike_rate":null,"percent_runs":null,"overs":4,"maidens":0,"runs_given":33,"wickets_taken":1,"economy":8.25,"percent_wickets":10,"catches":0,"opponent":"Kolkata Knight Riders"},{"player_name":"Harshal Patel","dismissal":null,"runs_scored":null,"balls_faced":null,"fours":null,"sixes":null,"strike_rate":null,"percent_runs":null,"overs":4,"maidens":0,"runs_given":44,"wickets_taken":0,"economy":11,"percent_wickets":null,"catches":0,"opponent":"Kolkata Knight Riders"},{"player_name":"Virat Kohli","dismissal":"c Iyer b Russell","runs_scored":54,"balls_faced":37,"fours":6,"sixes":0,"strike_rate":145.95,"percent_runs":"30.17%","overs":null,"maidens":null,"runs_given":null,"wickets_taken":null,"economy":null,"percent_wickets":null,"catches":0,"opponent":"Kolkata Knight Riders"},{"player_name":"Faf du Plessis","dismissal":"c Singh b Sharma","runs_scored":17,"balls_faced":7,"fours":1,"sixes":2,"strike_rate":242.86,"percent_runs":"9.50%","overs":null,"maidens":null,"runs_given":null,"wickets_taken":null,"economy":null,"percent_wickets":null,"catches":0,"opponent":"Kolkata Knight Riders"},{"player_name":"Shahbaz Ahmed","dismissal":"lbw b Sharma","runs_scored":2,"balls_faced":5,"fours":0,"sixes":0,"strike_rate":40,"percent_runs":"1.12%","overs":1,"maidens":0,"runs_given":25,"wickets_taken":0,"economy":25,"percent_wickets":null,"catches":0,"opponent":"Kolkata Knight Riders"},{"player_name":"Glenn Maxwell","dismissal":"c Wiese b Varun","runs_scored":5,"balls_faced":4,"fours":1,"sixes":0,"strike_rate":125,"percent_runs":"2.79%","overs":null,"maidens":null,"runs_given":null,"wickets_taken":null,"economy":null,"percent_wickets":null,"catches":1,"opponent":"Kolkata Knight Riders"},{"player_name":"Mahipal Lomror","dismissal":"c Russell b Varun","runs_scored":34,"balls_faced":18,"fours":1,"sixes":3,"strike_rate":188.89,"percent_runs":"18.99%","overs":null,"maidens":null,"runs_given":null,"wickets_taken":null,"economy":null,"percent_wickets":null,"catches":0,"opponent":"Kolkata Knight Riders"},{"player_name":"Dinesh Karthik","dismissal":"c Singh b Varun","runs_scored":22,"balls_faced":18,"fours":1,"sixes":1,"strike_rate":122.22,"percent_runs":"12.29%","overs":null,"maidens":null,"runs_given":null,"wickets_taken":null,"economy":null,"percent_wickets":null,"catches":0,"opponent":"Kolkata Knight Riders"},{"player_name":"Suyash Prabhudessai","dismissal":"run out","runs_scored":10,"balls_faced":9,"fours":1,"sixes":0,"strike_rate":111.11,"percent_runs":"5.59%","overs":null,"maidens":null,"runs_given":null,"wickets_taken":null,"economy":null,"percent_wickets":null,"catches":0,"opponent":"Kolkata Knight Riders"},{"player_name":"Wanindu Hasaranga","dismissal":"c sub b Russell","runs_scored":5,"balls_faced":4,"fours":0,"sixes":0,"strike_rate":125,"percent_runs":"2.79%","overs":4,"maidens":0,"runs_given":24,"wickets_taken":2,"economy":6,"percent_wickets":20,"catches":0,"opponent":"Kolkata Knight Riders"},{"player_name":"David Willey","dismissal":"not out","runs_scored":11,"balls_faced":10,"fours":1,"sixes":0,"strike_rate":110,"percent_runs":"6.15%","overs":3,"maidens":0,"runs_given":31,"wickets_taken":0,"economy":10.33,"percent_wickets":null,"catches":1,"opponent":"Kolkata Knight Riders"},{"player_name":"Vijaykumar Vyshak","dismissal":"not out","runs_scored":13,"balls_faced":8,"fours":0,"sixes":1,"strike_rate":162.5,"percent_runs":"7.26%","overs":4,"maidens":0,"runs_given":41,"wickets_taken":2,"economy":10.25,"percent_wickets":20,"catches":1,"opponent":"Kolkata Knight Riders"},{"player_name":"Vaibhav Arora","dismissal":null,"runs_scored":null,"balls_faced":null,"fours":null,"sixes":null,"strike_rate":null,"percent_runs":null,"overs":2,"maidens":0,"runs_given":22,"wickets_taken":0,"economy":11,"percent_wickets":null,"catches":0,"opponent":"Royal Challengers Bangalore"},{"player_name":"Umesh Yadav","dismissal":null,"runs_scored":null,"balls_faced":null,"fours":null,"sixes":null,"strike_rate":null,"percent_runs":null,"overs":1,"maidens":0,"runs_given":19,"wickets_taken":0,"economy":19,"percent_wickets":null,"catches":0,"opponent":"Royal Challengers Bangalore"},{"player_name":"Suyash Sharma","dismissal":null,"runs_scored":null,"balls_faced":null,"fours":null,"sixes":null,"strike_rate":null,"percent_runs":null,"overs":4,"maidens":0,"runs_given":30,"wickets_taken":2,"economy":7.5,"percent_wickets":20,"catches":0,"opponent":"Royal Challengers Bangalore"},{"player_name":"Varun Chakravarthy","dismissal":null,"runs_scored":null,"balls_faced":null,"fours":null,"sixes":null,"strike_rate":null,"percent_runs":null,"overs":4,"maidens":0,"runs_given":27,"wickets_taken":3,"economy":6.75,"percent_wickets":30,"catches":0,"opponent":"Royal Challengers Bangalore"},{"player_name":"Andre Russell","dismissal":"b Mohammed Siraj","runs_scored":1,"balls_faced":2,"fours":0,"sixes":0,"strike_rate":50,"percent_runs":"0.50%","overs":4,"maidens":0,"runs_given":29,"wickets_taken":2,"economy":7.25,"percent_wickets":20,"catches":1,"opponent":"Royal Challengers Bangalore"},{"player_name":"Sunil Narine","dismissal":null,"runs_scored":null,"balls_faced":null,"fours":null,"sixes":null,"strike_rate":null,"percent_runs":null,"overs":4,"maidens":0,"runs_given":41,"wickets_taken":0,"economy":10.25,"percent_wickets":null,"catches":0,"opponent":"Royal Challengers Bangalore"},{"player_name":"Nitish Rana","dismissal":"c Vijaykumar Vyshak b Wanindu Hasaranga","runs_scored":48,"balls_faced":21,"fours":3,"sixes":4,"strike_rate":228.57,"percent_runs":"24.00%","overs":1,"maidens":0,"runs_given":8,"wickets_taken":0,"economy":8,"percent_wickets":null,"catches":0,"opponent":"Royal Challengers Bangalore"}]}