{"match_details":{"batting_first":"Rajasthan Royals","batting_second":"Delhi Capitals","venue":"Sawai Mansingh Stadium, Jaipur","date":"22nd April, 2019","winner":"Delhi Capitals"},"players":[{"player_name":"Ajinkya Rahane","dismissal":"not out","runs_scored":105,"balls_faced":63,"fours":11,"sixes":3,"strike_rate":166.67,"percent_runs":"54.97%","overs":null,"maidens":null,"runs_given":null,"wickets_taken":null,"economy":null,"percent_wickets":null,"catches":0,"opponent":"Delhi Capitals"},{"player_name":"Sanju Samson","dismissal":"run out","runs_scored":0,"balls_faced":0,"fours":0,"sixes":0,"strike_rate":0,"percent_runs":"","overs":null,"maidens":null,"runs_given":null,"wickets_taken":null,"economy":null,"percent_wickets":null,"catches":0,"opponent":"Delhi Capitals"},{"player_name":"Steve Smith","dismissal":"c Morris b Patel","runs_scored":50,"balls_faced":32,"fours":8,"sixes":0,"strike_rate":156.25,"percent_runs":"26.18%","overs":null,"maidens":null,"runs_given":null,"wickets_taken":null,"economy":null,"percent_wickets":null,"catches":0,"opponent":"Delhi Capitals"},{"player_name":"Ben Stokes","dismissal":"c Iyer b Morris","runs_scored":8,"balls_faced":8,"fours":1,"sixes":0,"strike_rate":100,"percent_runs":"4.19%","overs":null,"maidens":null,"runs_given":null,"wickets_taken":null,"economy":null,"percent_wickets":null,"catches":1,"opponent":"Delhi Capitals"},{"player_name":"Ashton Turner","dismissal":"c Rutherford b Sharma","runs_scored":0,"balls_faced":1,"fours":0,"sixes":0,"strike_rate":0,"percent_runs":"","overs":null,"maidens":null,"runs_given":null,"wickets_taken":null,"economy":null,"percent_wickets":null,"catches":0,"opponent":"Delhi Capitals"},{"player_name":"Ishant Sharma","dismissal":null,"runs_scored":null,"balls_faced":null,"fours":null,"sixes":null,"strike_rate":null,"percent_runs":null,"overs":4,"maidens":0,"runs_given":29,"wickets_taken":1,"economy":7.25,"percent_wickets":10,"catches":0,"opponent":"Rajasthan Royals"},{"player_name":"Kagiso Rabada","dismissal":null,"runs_scored":null,"balls_faced":null,"fours":null,"sixes":null,"strike_rate":null,"percent_runs":null,"overs":4,"maidens":0,"runs_given":37,"wickets_taken":2,"economy":9.25,"percent_wickets":20,"catches":0,"opponent":"Rajasthan Royals"},{"player_name":"Axar Patel","dismissal":null,"runs_scored":null,"balls_faced":null,"fours":null,"sixes":null,"strike_rate":null,"percent_runs":null,"overs":4,"maidens":0,"runs_given":39,"wickets_taken":1,"economy":9.75,"percent_wickets":10,"catches":0,"opponent":"Rajasthan Royals"},{"player_name":"Amit Mishra","dismissal":null,"runs_scored":null,"balls_faced":null,"fours":null,"sixes":null,"strike_rate":null,"percent_runs":null,"overs":3,"maidens":0,"runs_given":28,"wickets_taken":0,"economy":9.33,"percent_wickets":null,"catches":0,"opponent":"Rajasthan Royals"},{"player_name":"Chris Morris","dismissal":null,"runs_scored":null,"balls_faced":null,"fours":null,"sixes":null,"strike_rate":null,"percent_runs":null,"overs":4,"maidens":0,"runs_given":41,"wickets_taken":1,"economy":10.25,"percent_wickets":10,"catches":1,"opponent":"Rajasthan Royals"},{"player_name":"Prithvi Shaw","dismissal":"c Parag b Gopal","runs_scored":42,"balls_faced":39,"fours":4,"sixes":1,"strike_rate":107.69,"percent_runs":"21.76%","overs":null,"maidens":null,"runs_given":null,"wickets_taken":null,"economy":null,"percent_wickets":null,"catches":0,"opponent":"Rajasthan Royals"},{"player_name":"Shikhar Dhawan","dismissal":"st †Samson b Gopal","runs_scored":54,"balls_faced":27,"fours":8,"sixes":2,"strike_rate":200,"percent_runs":"27.98%","overs":null,"maidens":null,"runs_given":null,"wickets_taken":null,"economy":null,"percent_wickets":null,"catches":0,"opponent":"Rajasthan Royals"},{"player_name":"Shreyas Iyer","dismissal":"c Stokes b Parag","runs_scored":4,"balls_faced":5,"fours":0,"sixes":0,"strike_rate":80,"percent_runs":"2.07%","overs":null,"maidens":null,"runs_given":null,"wickets_taken":null,"economy":null,"percent_wickets":null,"catches":1,"opponent":"Rajasthan Royals"},{"player_name":"Rishabh Pant","dismissal":"not out","runs_scored":78,"balls_faced":36,"fours":6,"sixes":4,"strike_rate":216.67,"percent_runs":"40.41%","overs":null,"maidens":null,"runs_given":null,"wickets_taken":null,"economy":null,"percent_wickets":null,"catches":0,"opponent":"Rajasthan Royals"},{"player_name":"Sherfane Rutherford","dismissal":"c Parag b Kulkarni","runs_scored":11,"balls_faced":5,"fours":1,"sixes":1,"strike_rate":220,"percent_runs":"5.70%","overs":1,"maidens":0,"runs_given":16,"wickets_taken":0,"economy":16,"percent_wickets":null,"catches":1,"opponent":"Rajasthan Royals"},{"player_name":"Colin Ingram","dismissal":"not out","runs_scored":3,"balls_faced":5,"fours":0,"sixes":0,"strike_rate":60,"percent_runs":"1.55%","overs":null,"maidens":null,"runs_given":null,"wickets_taken":null,"economy":null,"percent_wickets":null,"catches":0,"opponent":"Rajasthan Royals"},{"player_name":"Stuart Binny","dismissal":null,"runs_scored":null,"balls_faced":null,"fours":null,"sixes":null,"strike_rate":null,"percent_runs":null,"overs":1,"maidens":0,"runs_given":3,"wickets_taken":0,"economy":3,"percent_wickets":null,"catches":0,"opponent":"Delhi Capitals"},{"player_name":"Dhawal Kulkarni","dismissal":null,"runs_scored":null,"balls_faced":null,"fours":null,"sixes":null,"strike_rate":null,"percent_runs":null,"overs":4,"maidens":0,"runs_given":51,"wickets_taken":1,"economy":12.75,"percent_wickets":10,"catches":0,"opponent":"Delhi Capitals"},{"player_name":"Jaydev Unadkat","dismissal":null,"runs_scored":null,"balls_faced":null,"fours":null,"sixes":null,"strike_rate":null,"percent_runs":null,"overs":3.2,"maidens":0,"runs_given":36,"wickets_taken":0,"economy":10.8,"percent_wickets":null,"catches":0,"opponent":"Delhi Capitals"},{"player_name":"Shreyas Gopal","dismissal":null,"runs_scored":null,"balls_faced":null,"fours":null,"sixes":null,"strike_rate":null,"percent_runs":null,"overs":4,"maidens":0,"runs_given":47,"wickets_taken":2,"economy":11.75,"percent_wickets":20,"catches":0,"opponent":"Delhi Capitals"},{"player_name":"Jofra Archer","dismissal":null,"runs_scored":null,"balls_faced":null,"fours":null,"sixes":null,"strike_rate":null,"percent_runs":null,"overs":4,"maidens":0,"runs_given":31,"wickets_taken":0,"economy":7.75,"percent_wickets":null,"catches":0,"opponent":"Delhi Capitals"},{"player_name":"Riyan Parag","dismissal":"b Rabada","runs_scored":4,"balls_faced":3,"fours":1,"sixes":0,"strike_rate":133.33,"percent_runs":"2.09%","overs":3,"maidens":0,"runs_given":25,"wickets_taken":1,"economy":8.33,"percent_wickets":10,"catches":2,"opponent":"Delhi Capitals"}]}