{"match_details":{"batting_first":"Rajasthan Royals","batting_second":"Mumbai Indians","venue":"Sawai Mansingh Stadium, Jaipur","date":"20th May, 2012","winner":"Mumbai Indians"},"players":[{"player_name":"Rahul Dravid","dismissal":"c †Karthik b Kulkarni","runs_scored":5,"balls_faced":5,"fours":1,"sixes":0,"strike_rate":100,"percent_runs":"3.09%","overs":null,"maidens":null,"runs_given":null,"wickets_taken":null,"economy":null,"percent_wickets":null,"catches":0,"opponent":"Mumbai Indians"},{"player_name":"Ajinkya Rahane","dismissal":"c Sharma b Kulkarni","runs_scored":13,"balls_faced":17,"fours":2,"sixes":0,"strike_rate":76.47,"percent_runs":"8.02%","overs":null,"maidens":null,"runs_given":null,"wickets_taken":null,"economy":null,"percent_wickets":null,"catches":0,"opponent":"Mumbai Indians"},{"player_name":"Owais Shah","dismissal":"not out","runs_scored":28,"balls_faced":24,"fours":1,"sixes":1,"strike_rate":116.67,"percent_runs":"17.28%","overs":null,"maidens":null,"runs_given":null,"wickets_taken":null,"economy":null,"percent_wickets":null,"catches":0,"opponent":"Mumbai Indians"},{"player_name":"Ashok Menaria","dismissal":"c & b Kulkarni","runs_scored":21,"balls_faced":20,"fours":1,"sixes":1,"strike_rate":105,"percent_runs":"12.96%","overs":null,"maidens":null,"runs_given":null,"wickets_taken":null,"economy":null,"percent_wickets":null,"catches":0,"opponent":"Mumbai Indians"},{"player_name":"Dishant Yagnik","dismissal":"c & b Malinga","runs_scored":6,"balls_faced":3,"fours":1,"sixes":0,"strike_rate":200,"percent_runs":"3.70%","overs":null,"maidens":null,"runs_given":null,"wickets_taken":null,"economy":null,"percent_wickets":null,"catches":0,"opponent":"Mumbai Indians"},{"player_name":"R P Singh","dismissal":null,"runs_scored":null,"balls_faced":null,"fours":null,"sixes":null,"strike_rate":null,"percent_runs":null,"overs":3,"maidens":0,"runs_given":32,"wickets_taken":0,"economy":10.67,"percent_wickets":null,"catches":0,"opponent":"Rajasthan Royals"},{"player_name":"Dhawal Kulkarni","dismissal":null,"runs_scored":null,"balls_faced":null,"fours":null,"sixes":null,"strike_rate":null,"percent_runs":null,"overs":4,"maidens":1,"runs_given":18,"wickets_taken":3,"economy":4.5,"percent_wickets":30,"catches":0,"opponent":"Rajasthan Royals"},{"player_name":"Lasith Malinga","dismissal":null,"runs_scored":null,"balls_faced":null,"fours":null,"sixes":null,"strike_rate":null,"percent_runs":null,"overs":4,"maidens":0,"runs_given":32,"wickets_taken":1,"economy":8,"percent_wickets":10,"catches":0,"opponent":"Rajasthan Royals"},{"player_name":"Harbhajan Singh","dismissal":null,"runs_scored":null,"balls_faced":null,"fours":null,"sixes":null,"strike_rate":null,"percent_runs":null,"overs":3,"maidens":0,"runs_given":31,"wickets_taken":0,"economy":10.33,"percent_wickets":null,"catches":0,"opponent":"Rajasthan Royals"},{"player_name":"Kieron Pollard","dismissal":null,"runs_scored":null,"balls_faced":null,"fours":null,"sixes":null,"strike_rate":null,"percent_runs":null,"overs":3,"maidens":0,"runs_given":29,"wickets_taken":1,"economy":9.67,"percent_wickets":10,"catches":0,"opponent":"Rajasthan Royals"},{"player_name":"James Franklin","dismissal":null,"runs_scored":null,"balls_faced":null,"fours":null,"sixes":null,"strike_rate":null,"percent_runs":null,"overs":1,"maidens":0,"runs_given":6,"wickets_taken":0,"economy":6,"percent_wickets":null,"catches":0,"opponent":"Rajasthan Royals"},{"player_name":"Sachin Tendulkar","dismissal":"not out","runs_scored":58,"balls_faced":51,"fours":6,"sixes":0,"strike_rate":113.73,"percent_runs":"35.58%","overs":null,"maidens":null,"runs_given":null,"wickets_taken":null,"economy":null,"percent_wickets":null,"catches":0,"opponent":"Rajasthan Royals"},{"player_name":"Dwayne Smith","dismissal":"not out","runs_scored":87,"balls_faced":58,"fours":10,"sixes":3,"strike_rate":150,"percent_runs":"53.37%","overs":2,"maidens":0,"runs_given":13,"wickets_taken":0,"economy":6.5,"percent_wickets":null,"catches":1,"opponent":"Rajasthan Royals"},{"player_name":"Rohit Sharma","dismissal":null,"runs_scored":null,"balls_faced":null,"fours":null,"sixes":null,"strike_rate":null,"percent_runs":null,"overs":null,"maidens":null,"runs_given":null,"wickets_taken":null,"economy":null,"percent_wickets":null,"catches":1,"opponent":"Rajasthan Royals"},{"player_name":"Dinesh Karthik†","dismissal":null,"runs_scored":null,"balls_faced":null,"fours":null,"sixes":null,"strike_rate":null,"percent_runs":null,"overs":null,"maidens":null,"runs_given":null,"wickets_taken":null,"economy":null,"percent_wickets":null,"catches":1,"opponent":"Rajasthan Royals"},{"player_name":"Ambati Rayudu","dismissal":null,"runs_scored":null,"balls_faced":null,"fours":null,"sixes":null,"strike_rate":null,"percent_runs":null,"overs":null,"maidens":null,"runs_given":null,"wickets_taken":null,"economy":null,"percent_wickets":null,"catches":0,"opponent":"Rajasthan Royals"},{"player_name":"Harbhajan Singh*","dismissal":null,"runs_scored":null,"balls_faced":null,"fours":null,"sixes":null,"strike_rate":null,"percent_runs":null,"overs":null,"maidens":null,"runs_given":null,"wickets_taken":null,"economy":null,"percent_wickets":null,"catches":0,"opponent":"Rajasthan Royals"},{"player_name":"Ajit Chandila","dismissal":null,"runs_scored":null,"balls_faced":null,"fours":null,"sixes":null,"strike_rate":null,"percent_runs":null,"overs":2,"maidens":0,"runs_given":24,"wickets_taken":0,"economy":12,"percent_wickets":null,"catches":0,"opponent":"Mumbai Indians"},{"player_name":"Shane Watson","dismissal":"c Smith b Pollard","runs_scored":45,"balls_faced":36,"fours":4,"sixes":2,"strike_rate":125,"percent_runs":"27.78%","overs":3,"maidens":0,"runs_given":17,"wickets_taken":0,"economy":5.67,"percent_wickets":null,"catches":0,"opponent":"Mumbai Indians"},{"player_name":"Shaun Tait","dismissal":null,"runs_scored":null,"balls_faced":null,"fours":null,"sixes":null,"strike_rate":null,"percent_runs":null,"overs":4,"maidens":0,"runs_given":40,"wickets_taken":0,"economy":10,"percent_wickets":null,"catches":0,"opponent":"Mumbai Indians"},{"player_name":"Brad Hogg","dismissal":"not out","runs_scored":0,"balls_faced":0,"fours":0,"sixes":0,"strike_rate":0,"percent_runs":"","overs":4,"maidens":0,"runs_given":30,"wickets_taken":0,"economy":7.5,"percent_wickets":null,"catches":0,"opponent":"Mumbai Indians"},{"player_name":"Siddharth Trivedi","dismissal":null,"runs_scored":null,"balls_faced":null,"fours":null,"sixes":null,"strike_rate":null,"percent_runs":null,"overs":4,"maidens":0,"runs_given":37,"wickets_taken":0,"economy":9.25,"percent_wickets":null,"catches":0,"opponent":"Mumbai Indians"},{"player_name":"Stuart Binny","dismissal":"run out","runs_scored":30,"balls_faced":17,"fours":3,"sixes":2,"strike_rate":176.47,"percent_runs":"18.52%","overs":1,"maidens":0,"runs_given":13,"wickets_taken":0,"economy":13,"percent_wickets":null,"catches":0,"opponent":"Mumbai Indians"}]}