{"match_details":{"batting_first":"Pune Warriors","batting_second":"Royal Challengers Bangalore","venue":"M Chinnaswamy Stadium, Bengaluru, Bangalore","date":"17th April, 2012","winner":"Royal Challengers Bangalore"},"players":[{"player_name":"Robin Uthappa","dismissal":"c Patel b Vettori","runs_scored":69,"balls_faced":45,"fours":9,"sixes":2,"strike_rate":153.33,"percent_runs":"37.91%","overs":null,"maidens":null,"runs_given":null,"wickets_taken":null,"economy":null,"percent_wickets":null,"catches":1,"opponent":"Royal Challengers Bangalore"},{"player_name":"Jesse Ryder","dismissal":"c Agarwal b Patel","runs_scored":34,"balls_faced":22,"fours":4,"sixes":1,"strike_rate":154.55,"percent_runs":"18.68%","overs":null,"maidens":null,"runs_given":null,"wickets_taken":null,"economy":null,"percent_wickets":null,"catches":0,"opponent":"Royal Challengers Bangalore"},{"player_name":"Sourav Ganguly","dismissal":"c Agarwal b Vinay Kumar","runs_scored":6,"balls_faced":8,"fours":0,"sixes":0,"strike_rate":75,"percent_runs":"3.30%","overs":null,"maidens":null,"runs_given":null,"wickets_taken":null,"economy":null,"percent_wickets":null,"catches":0,"opponent":"Royal Challengers Bangalore"},{"player_name":"Steve Smith","dismissal":"run out","runs_scored":16,"balls_faced":14,"fours":0,"sixes":1,"strike_rate":114.29,"percent_runs":"8.79%","overs":null,"maidens":null,"runs_given":null,"wickets_taken":null,"economy":null,"percent_wickets":null,"catches":0,"opponent":"Royal Challengers Bangalore"},{"player_name":"Mithun Manhas","dismissal":"not out","runs_scored":6,"balls_faced":4,"fours":1,"sixes":0,"strike_rate":150,"percent_runs":"3.30%","overs":null,"maidens":null,"runs_given":null,"wickets_taken":null,"economy":null,"percent_wickets":null,"catches":1,"opponent":"Royal Challengers Bangalore"},{"player_name":"Zaheer Khan","dismissal":null,"runs_scored":null,"balls_faced":null,"fours":null,"sixes":null,"strike_rate":null,"percent_runs":null,"overs":4,"maidens":0,"runs_given":34,"wickets_taken":0,"economy":8.5,"percent_wickets":null,"catches":0,"opponent":"Pune Warriors"},{"player_name":"Vinay Kumar","dismissal":null,"runs_scored":null,"balls_faced":null,"fours":null,"sixes":null,"strike_rate":null,"percent_runs":null,"overs":4,"maidens":0,"runs_given":34,"wickets_taken":2,"economy":8.5,"percent_wickets":20,"catches":0,"opponent":"Pune Warriors"},{"player_name":"Harshal Patel","dismissal":null,"runs_scored":null,"balls_faced":null,"fours":null,"sixes":null,"strike_rate":null,"percent_runs":null,"overs":4,"maidens":0,"runs_given":29,"wickets_taken":1,"economy":7.25,"percent_wickets":10,"catches":1,"opponent":"Pune Warriors"},{"player_name":"Daniel Vettori","dismissal":null,"runs_scored":null,"balls_faced":null,"fours":null,"sixes":null,"strike_rate":null,"percent_runs":null,"overs":4,"maidens":0,"runs_given":34,"wickets_taken":1,"economy":8.5,"percent_wickets":10,"catches":0,"opponent":"Pune Warriors"},{"player_name":"Kotarangada Appanna","dismissal":null,"runs_scored":null,"balls_faced":null,"fours":null,"sixes":null,"strike_rate":null,"percent_runs":null,"overs":2,"maidens":0,"runs_given":23,"wickets_taken":0,"economy":11.5,"percent_wickets":null,"catches":0,"opponent":"Pune Warriors"},{"player_name":"Tillakaratne Dilshan","dismissal":"c †Uthappa b Dinda","runs_scored":4,"balls_faced":8,"fours":0,"sixes":0,"strike_rate":50,"percent_runs":"2.15%","overs":2,"maidens":0,"runs_given":24,"wickets_taken":0,"economy":12,"percent_wickets":null,"catches":0,"opponent":"Pune Warriors"},{"player_name":"Chris Gayle","dismissal":"b Nehra","runs_scored":81,"balls_faced":48,"fours":4,"sixes":8,"strike_rate":168.75,"percent_runs":"43.55%","overs":null,"maidens":null,"runs_given":null,"wickets_taken":null,"economy":null,"percent_wickets":null,"catches":0,"opponent":"Pune Warriors"},{"player_name":"Mayank Agarwal","dismissal":"c Manhas b Samuels","runs_scored":9,"balls_faced":10,"fours":0,"sixes":1,"strike_rate":90,"percent_runs":"4.84%","overs":null,"maidens":null,"runs_given":null,"wickets_taken":null,"economy":null,"percent_wickets":null,"catches":2,"opponent":"Pune Warriors"},{"player_name":"Virat Kohli","dismissal":"c Sharma b Mathews","runs_scored":16,"balls_faced":19,"fours":1,"sixes":0,"strike_rate":84.21,"percent_runs":"8.60%","overs":null,"maidens":null,"runs_given":null,"wickets_taken":null,"economy":null,"percent_wickets":null,"catches":1,"opponent":"Pune Warriors"},{"player_name":"Saurabh Tiwary","dismissal":"not out","runs_scored":36,"balls_faced":23,"fours":1,"sixes":2,"strike_rate":156.52,"percent_runs":"19.35%","overs":null,"maidens":null,"runs_given":null,"wickets_taken":null,"economy":null,"percent_wickets":null,"catches":0,"opponent":"Pune Warriors"},{"player_name":"AB de Villiers","dismissal":"not out","runs_scored":33,"balls_faced":14,"fours":2,"sixes":3,"strike_rate":235.71,"percent_runs":"17.74%","overs":null,"maidens":null,"runs_given":null,"wickets_taken":null,"economy":null,"percent_wickets":null,"catches":0,"opponent":"Pune Warriors"},{"player_name":"Daniel Vettori*","dismissal":null,"runs_scored":null,"balls_faced":null,"fours":null,"sixes":null,"strike_rate":null,"percent_runs":null,"overs":null,"maidens":null,"runs_given":null,"wickets_taken":null,"economy":null,"percent_wickets":null,"catches":0,"opponent":"Pune Warriors"},{"player_name":"Ashok Dinda","dismissal":null,"runs_scored":null,"balls_faced":null,"fours":null,"sixes":null,"strike_rate":null,"percent_runs":null,"overs":4,"maidens":0,"runs_given":28,"wickets_taken":1,"economy":7,"percent_wickets":10,"catches":0,"opponent":"Royal Challengers Bangalore"},{"player_name":"Ashish Nehra","dismissal":null,"runs_scored":null,"balls_faced":null,"fours":null,"sixes":null,"strike_rate":null,"percent_runs":null,"overs":4,"maidens":0,"runs_given":54,"wickets_taken":1,"economy":13.5,"percent_wickets":10,"catches":0,"opponent":"Royal Challengers Bangalore"},{"player_name":"Bhuvneshwar Kumar","dismissal":"not out","runs_scored":0,"balls_faced":0,"fours":0,"sixes":0,"strike_rate":0,"percent_runs":"","overs":4,"maidens":0,"runs_given":27,"wickets_taken":0,"economy":6.75,"percent_wickets":null,"catches":0,"opponent":"Royal Challengers Bangalore"},{"player_name":"Marlon Samuels","dismissal":"run out","runs_scored":34,"balls_faced":20,"fours":1,"sixes":2,"strike_rate":170,"percent_runs":"18.68%","overs":2,"maidens":0,"runs_given":5,"wickets_taken":1,"economy":2.5,"percent_wickets":10,"catches":0,"opponent":"Royal Challengers Bangalore"},{"player_name":"Angelo Mathews","dismissal":"c Kohli b Vinay Kumar","runs_scored":10,"balls_faced":7,"fours":0,"sixes":1,"strike_rate":142.86,"percent_runs":"5.49%","overs":4,"maidens":0,"runs_given":35,"wickets_taken":1,"economy":8.75,"percent_wickets":10,"catches":0,"opponent":"Royal Challengers Bangalore"},{"player_name":"Rahul Sharma","dismissal":null,"runs_scored":null,"balls_faced":null,"fours":null,"sixes":null,"strike_rate":null,"percent_runs":null,"overs":2,"maidens":0,"runs_given":35,"wickets_taken":0,"economy":17.5,"percent_wickets":null,"catches":1,"opponent":"Royal Challengers Bangalore"}]}