{"match_details":{"batting_first":"Kings XI Punjab","batting_second":"Mumbai Indians","venue":"Punjab Cricket Association IS Bindra Stadium, Mohali, Chandigarh","date":"25th April, 2008","winner":"Kings XI Punjab"},"players":[{"player_name":"Karan Goel","dismissal":"run out","runs_scored":18,"balls_faced":21,"fours":1,"sixes":1,"strike_rate":85.71,"percent_runs":"9.89%","overs":null,"maidens":null,"runs_given":null,"wickets_taken":null,"economy":null,"percent_wickets":null,"catches":0,"opponent":"Mumbai Indians"},{"player_name":"Kumar Sangakkara","dismissal":"c Kulkarni b Harbhajan Singh","runs_scored":94,"balls_faced":56,"fours":13,"sixes":1,"strike_rate":167.86,"percent_runs":"51.65%","overs":null,"maidens":null,"runs_given":null,"wickets_taken":null,"economy":null,"percent_wickets":null,"catches":0,"opponent":"Mumbai Indians"},{"player_name":"Yuvraj Singh","dismissal":"c Bravo b Pollock","runs_scored":18,"balls_faced":9,"fours":1,"sixes":1,"strike_rate":200,"percent_runs":"9.89%","overs":null,"maidens":null,"runs_given":null,"wickets_taken":null,"economy":null,"percent_wickets":null,"catches":1,"opponent":"Mumbai Indians"},{"player_name":"Ramnaresh Sarwan","dismissal":"c Harbhajan Singh b Nehra","runs_scored":7,"balls_faced":9,"fours":0,"sixes":0,"strike_rate":77.78,"percent_runs":"3.85%","overs":null,"maidens":null,"runs_given":null,"wickets_taken":null,"economy":null,"percent_wickets":null,"catches":1,"opponent":"Mumbai Indians"},{"player_name":"Mahela Jayawardene","dismissal":"c sub b Harbhajan Singh","runs_scored":12,"balls_faced":7,"fours":0,"sixes":1,"strike_rate":171.43,"percent_runs":"6.59%","overs":null,"maidens":null,"runs_given":null,"wickets_taken":null,"economy":null,"percent_wickets":null,"catches":0,"opponent":"Mumbai Indians"},{"player_name":"Sunny Sohal","dismissal":"c Nehra b Kulkarni","runs_scored":0,"balls_faced":4,"fours":0,"sixes":0,"strike_rate":0,"percent_runs":"","overs":null,"maidens":null,"runs_given":null,"wickets_taken":null,"economy":null,"percent_wickets":null,"catches":0,"opponent":"Mumbai Indians"},{"player_name":"Luke Ronchi","dismissal":"run out","runs_scored":11,"balls_faced":8,"fours":1,"sixes":1,"strike_rate":137.5,"percent_runs":"9.48%","overs":null,"maidens":null,"runs_given":null,"wickets_taken":null,"economy":null,"percent_wickets":null,"catches":1,"opponent":"Kings XI Punjab"},{"player_name":"Sanath Jayasuriya","dismissal":"c & b Lee","runs_scored":1,"balls_faced":7,"fours":0,"sixes":0,"strike_rate":14.29,"percent_runs":"0.86%","overs":null,"maidens":null,"runs_given":null,"wickets_taken":null,"economy":null,"percent_wickets":null,"catches":0,"opponent":"Kings XI Punjab"},{"player_name":"Robin Uthappa","dismissal":"c Sarwan b VR Singh","runs_scored":21,"balls_faced":18,"fours":2,"sixes":1,"strike_rate":116.67,"percent_runs":"18.10%","overs":null,"maidens":null,"runs_given":null,"wickets_taken":null,"economy":null,"percent_wickets":null,"catches":0,"opponent":"Kings XI Punjab"},{"player_name":"Dwayne Bravo","dismissal":"b Chawla","runs_scored":23,"balls_faced":21,"fours":4,"sixes":0,"strike_rate":109.52,"percent_runs":"19.83%","overs":3,"maidens":0,"runs_given":27,"wickets_taken":0,"economy":9,"percent_wickets":null,"catches":1,"opponent":"Kings XI Punjab"},{"player_name":"Saurabh Tiwary","dismissal":"b Chawla","runs_scored":17,"balls_faced":10,"fours":2,"sixes":1,"strike_rate":170,"percent_runs":"14.66%","overs":null,"maidens":null,"runs_given":null,"wickets_taken":null,"economy":null,"percent_wickets":null,"catches":0,"opponent":"Kings XI Punjab"},{"player_name":"Shaun Pollock","dismissal":"c Yuvraj Singh b Sreesanth","runs_scored":22,"balls_faced":21,"fours":2,"sixes":1,"strike_rate":104.76,"percent_runs":"18.97%","overs":4,"maidens":0,"runs_given":40,"wickets_taken":1,"economy":10,"percent_wickets":10,"catches":0,"opponent":"Kings XI Punjab"},{"player_name":"Abhishek Nayar","dismissal":"c Chawla b Pathan","runs_scored":2,"balls_faced":3,"fours":0,"sixes":0,"strike_rate":66.67,"percent_runs":"1.72%","overs":null,"maidens":null,"runs_given":null,"wickets_taken":null,"economy":null,"percent_wickets":null,"catches":0,"opponent":"Kings XI Punjab"},{"player_name":"Harbhajan Singh","dismissal":"lbw b Pathan","runs_scored":0,"balls_faced":1,"fours":0,"sixes":0,"strike_rate":0,"percent_runs":"","overs":4,"maidens":0,"runs_given":32,"wickets_taken":3,"economy":8,"percent_wickets":30,"catches":1,"opponent":"Kings XI Punjab"},{"player_name":"Musavir Khote","dismissal":"hit wicket b Sreesanth","runs_scored":8,"balls_faced":7,"fours":1,"sixes":0,"strike_rate":114.29,"percent_runs":"6.90%","overs":2,"maidens":0,"runs_given":22,"wickets_taken":0,"economy":11,"percent_wickets":null,"catches":0,"opponent":"Kings XI Punjab"},{"player_name":"Dhawal Kulkarni","dismissal":"not out","runs_scored":2,"balls_faced":16,"fours":0,"sixes":0,"strike_rate":12.5,"percent_runs":"1.72%","overs":4,"maidens":0,"runs_given":37,"wickets_taken":2,"economy":9.25,"percent_wickets":20,"catches":2,"opponent":"Kings XI Punjab"},{"player_name":"Ashish Nehra","dismissal":"not out","runs_scored":2,"balls_faced":10,"fours":0,"sixes":0,"strike_rate":20,"percent_runs":"1.72%","overs":3,"maidens":0,"runs_given":22,"wickets_taken":2,"economy":7.33,"percent_wickets":20,"catches":1,"opponent":"Kings XI Punjab"},{"player_name":"Brett Lee","dismissal":null,"runs_scored":null,"balls_faced":null,"fours":null,"sixes":null,"strike_rate":null,"percent_runs":null,"overs":4,"maidens":0,"runs_given":9,"wickets_taken":1,"economy":2.25,"percent_wickets":10,"catches":0,"opponent":"Mumbai Indians"},{"player_name":"Irfan Pathan","dismissal":"c Kulkarni b Nehra","runs_scored":6,"balls_faced":3,"fours":0,"sixes":0,"strike_rate":200,"percent_runs":"3.30%","overs":4,"maidens":1,"runs_given":19,"wickets_taken":2,"economy":4.75,"percent_wickets":20,"catches":0,"opponent":"Mumbai Indians"},{"player_name":"Vikram Singh","dismissal":"run out","runs_scored":4,"balls_faced":2,"fours":1,"sixes":0,"strike_rate":200,"percent_runs":"2.20%","overs":4,"maidens":0,"runs_given":40,"wickets_taken":1,"economy":10,"percent_wickets":10,"catches":0,"opponent":"Mumbai Indians"},{"player_name":"Sreesanth","dismissal":"c †Ronchi b Kulkarni","runs_scored":0,"balls_faced":1,"fours":0,"sixes":0,"strike_rate":0,"percent_runs":"","overs":4,"maidens":0,"runs_given":31,"wickets_taken":2,"economy":7.75,"percent_wickets":20,"catches":0,"opponent":"Mumbai Indians"},{"player_name":"Piyush Chawla","dismissal":"lbw b Harbhajan Singh","runs_scored":0,"balls_faced":1,"fours":0,"sixes":0,"strike_rate":0,"percent_runs":"","overs":4,"maidens":0,"runs_given":16,"wickets_taken":2,"economy":4,"percent_wickets":20,"catches":1,"opponent":"Mumbai Indians"}]}