{"match_details":{"batting_first":"Sunrisers Hyderabad","batting_second":"Delhi Capitals","venue":"Sheikh Zayed Stadium, Abu Dhabi","date":"29th September, 2020","winner":"Sunrisers Hyderabad"},"players":[{"player_name":"David Warner","dismissal":"c †Pant b Mishra","runs_scored":45,"balls_faced":33,"fours":3,"sixes":2,"strike_rate":136.36,"percent_runs":"27.78%","overs":null,"maidens":null,"runs_given":null,"wickets_taken":null,"economy":null,"percent_wickets":null,"catches":0,"opponent":"Delhi Capitals"},{"player_name":"Jonny Bairstow","dismissal":"c Nortje b Rabada","runs_scored":53,"balls_faced":48,"fours":2,"sixes":1,"strike_rate":110.42,"percent_runs":"32.72%","overs":null,"maidens":null,"runs_given":null,"wickets_taken":null,"economy":null,"percent_wickets":null,"catches":2,"opponent":"Delhi Capitals"},{"player_name":"Manish Pandey","dismissal":"c Rabada b Mishra","runs_scored":3,"balls_faced":5,"fours":0,"sixes":0,"strike_rate":60,"percent_runs":"1.85%","overs":null,"maidens":null,"runs_given":null,"wickets_taken":null,"economy":null,"percent_wickets":null,"catches":1,"opponent":"Delhi Capitals"},{"player_name":"Kane Williamson","dismissal":"c Patel b Rabada","runs_scored":41,"balls_faced":26,"fours":5,"sixes":0,"strike_rate":157.69,"percent_runs":"25.31%","overs":null,"maidens":null,"runs_given":null,"wickets_taken":null,"economy":null,"percent_wickets":null,"catches":0,"opponent":"Delhi Capitals"},{"player_name":"Abdul Samad","dismissal":"not out","runs_scored":12,"balls_faced":7,"fours":1,"sixes":1,"strike_rate":171.43,"percent_runs":"7.41%","overs":null,"maidens":null,"runs_given":null,"wickets_taken":null,"economy":null,"percent_wickets":null,"catches":1,"opponent":"Delhi Capitals"},{"player_name":"Priyam Garg","dismissal":null,"runs_scored":null,"balls_faced":null,"fours":null,"sixes":null,"strike_rate":null,"percent_runs":null,"overs":null,"maidens":null,"runs_given":null,"wickets_taken":null,"economy":null,"percent_wickets":null,"catches":1,"opponent":"Delhi Capitals"},{"player_name":"Ishant Sharma","dismissal":null,"runs_scored":null,"balls_faced":null,"fours":null,"sixes":null,"strike_rate":null,"percent_runs":null,"overs":3,"maidens":0,"runs_given":26,"wickets_taken":0,"economy":8.67,"percent_wickets":null,"catches":0,"opponent":"Sunrisers Hyderabad"},{"player_name":"Amit Mishra","dismissal":null,"runs_scored":null,"balls_faced":null,"fours":null,"sixes":null,"strike_rate":null,"percent_runs":null,"overs":4,"maidens":0,"runs_given":35,"wickets_taken":2,"economy":8.75,"percent_wickets":20,"catches":0,"opponent":"Sunrisers Hyderabad"},{"player_name":"Prithvi Shaw","dismissal":"c †Bairstow b Kumar","runs_scored":2,"balls_faced":5,"fours":0,"sixes":0,"strike_rate":40,"percent_runs":"1.36%","overs":null,"maidens":null,"runs_given":null,"wickets_taken":null,"economy":null,"percent_wickets":null,"catches":0,"opponent":"Sunrisers Hyderabad"},{"player_name":"Shikhar Dhawan","dismissal":"c †Bairstow b Rashid Khan","runs_scored":34,"balls_faced":31,"fours":4,"sixes":0,"strike_rate":109.68,"percent_runs":"23.13%","overs":null,"maidens":null,"runs_given":null,"wickets_taken":null,"economy":null,"percent_wickets":null,"catches":0,"opponent":"Sunrisers Hyderabad"},{"player_name":"Shreyas Iyer","dismissal":"c Abdul Samad b Rashid Khan","runs_scored":17,"balls_faced":21,"fours":2,"sixes":0,"strike_rate":80.95,"percent_runs":"11.56%","overs":null,"maidens":null,"runs_given":null,"wickets_taken":null,"economy":null,"percent_wickets":null,"catches":0,"opponent":"Sunrisers Hyderabad"},{"player_name":"Rishabh Pant","dismissal":"c Garg b Rashid Khan","runs_scored":28,"balls_faced":27,"fours":1,"sixes":2,"strike_rate":103.7,"percent_runs":"19.05%","overs":null,"maidens":null,"runs_given":null,"wickets_taken":null,"economy":null,"percent_wickets":null,"catches":1,"opponent":"Sunrisers Hyderabad"},{"player_name":"Shimron Hetmeyer","dismissal":"c Pandey b Kumar","runs_scored":21,"balls_faced":12,"fours":0,"sixes":2,"strike_rate":175,"percent_runs":"14.29%","overs":null,"maidens":null,"runs_given":null,"wickets_taken":null,"economy":null,"percent_wickets":null,"catches":0,"opponent":"Sunrisers Hyderabad"},{"player_name":"Marcus Stoinis","dismissal":"lbw b Natarajan","runs_scored":11,"balls_faced":9,"fours":1,"sixes":0,"strike_rate":122.22,"percent_runs":"7.48%","overs":3,"maidens":0,"runs_given":22,"wickets_taken":0,"economy":7.33,"percent_wickets":null,"catches":0,"opponent":"Sunrisers Hyderabad"},{"player_name":"Axar Patel","dismissal":"b Ahmed","runs_scored":5,"balls_faced":6,"fours":0,"sixes":0,"strike_rate":83.33,"percent_runs":"3.40%","overs":2,"maidens":0,"runs_given":14,"wickets_taken":0,"economy":7,"percent_wickets":null,"catches":1,"opponent":"Sunrisers Hyderabad"},{"player_name":"Kagiso Rabada","dismissal":"not out","runs_scored":15,"balls_faced":7,"fours":1,"sixes":1,"strike_rate":214.29,"percent_runs":"10.20%","overs":4,"maidens":0,"runs_given":21,"wickets_taken":2,"economy":5.25,"percent_wickets":20,"catches":1,"opponent":"Sunrisers Hyderabad"},{"player_name":"Anrich Nortje","dismissal":"not out","runs_scored":3,"balls_faced":2,"fours":0,"sixes":0,"strike_rate":150,"percent_runs":"2.04%","overs":4,"maidens":0,"runs_given":40,"wickets_taken":0,"economy":10,"percent_wickets":null,"catches":1,"opponent":"Sunrisers Hyderabad"},{"player_name":"Bhuvneshwar Kumar","dismissal":null,"runs_scored":null,"balls_faced":null,"fours":null,"sixes":null,"strike_rate":null,"percent_runs":null,"overs":4,"maidens":0,"runs_given":25,"wickets_taken":2,"economy":6.25,"percent_wickets":20,"catches":0,"opponent":"Delhi Capitals"},{"player_name":"Khaleel Ahmed","dismissal":null,"runs_scored":null,"balls_faced":null,"fours":null,"sixes":null,"strike_rate":null,"percent_runs":null,"overs":4,"maidens":0,"runs_given":43,"wickets_taken":1,"economy":10.75,"percent_wickets":10,"catches":0,"opponent":"Delhi Capitals"},{"player_name":"Thangarasu Natarajan","dismissal":null,"runs_scored":null,"balls_faced":null,"fours":null,"sixes":null,"strike_rate":null,"percent_runs":null,"overs":4,"maidens":0,"runs_given":25,"wickets_taken":1,"economy":6.25,"percent_wickets":10,"catches":0,"opponent":"Delhi Capitals"},{"player_name":"Abhishek Sharma","dismissal":"not out","runs_scored":1,"balls_faced":1,"fours":0,"sixes":0,"strike_rate":100,"percent_runs":"0.62%","overs":4,"maidens":0,"runs_given":34,"wickets_taken":0,"economy":8.5,"percent_wickets":null,"catches":0,"opponent":"Delhi Capitals"},{"player_name":"Rashid Khan","dismissal":null,"runs_scored":null,"balls_faced":null,"fours":null,"sixes":null,"strike_rate":null,"percent_runs":null,"overs":4,"maidens":0,"runs_given":14,"wickets_taken":3,"economy":3.5,"percent_wickets":30,"catches":0,"opponent":"Delhi Capitals"}]}