{"match_details":{"batting_first":"Rajasthan Royals","batting_second":"Gujarat Titans","venue":"Narendra Modi Stadium, Ahmedabad","date":"29th May, 2022","winner":"Gujarat Titans"},"players":[{"player_name":"Yashasvi Jaiswal","dismissal":"c Kishore b Dayal","runs_scored":22,"balls_faced":16,"fours":1,"sixes":2,"strike_rate":137.5,"percent_runs":"16.92%","overs":null,"maidens":null,"runs_given":null,"wickets_taken":null,"economy":null,"percent_wickets":null,"catches":1,"opponent":"Gujarat Titans"},{"player_name":"Jos Buttler","dismissal":"c †Saha b Pandya","runs_scored":39,"balls_faced":35,"fours":5,"sixes":0,"strike_rate":111.43,"percent_runs":"30.00%","overs":null,"maidens":null,"runs_given":null,"wickets_taken":null,"economy":null,"percent_wickets":null,"catches":0,"opponent":"Gujarat Titans"},{"player_name":"Sanju Samson","dismissal":"c Kishore b Pandya","runs_scored":14,"balls_faced":11,"fours":2,"sixes":0,"strike_rate":127.27,"percent_runs":"10.77%","overs":null,"maidens":null,"runs_given":null,"wickets_taken":null,"economy":null,"percent_wickets":null,"catches":0,"opponent":"Gujarat Titans"},{"player_name":"Devdutt Padikkal","dismissal":"c Mohammed Shami b Rashid Khan","runs_scored":2,"balls_faced":10,"fours":0,"sixes":0,"strike_rate":20,"percent_runs":"1.54%","overs":null,"maidens":null,"runs_given":null,"wickets_taken":null,"economy":null,"percent_wickets":null,"catches":0,"opponent":"Gujarat Titans"},{"player_name":"Shimron Hetmeyer","dismissal":"c & b Pandya","runs_scored":11,"balls_faced":12,"fours":2,"sixes":0,"strike_rate":91.67,"percent_runs":"8.46%","overs":null,"maidens":null,"runs_given":null,"wickets_taken":null,"economy":null,"percent_wickets":null,"catches":0,"opponent":"Gujarat Titans"},{"player_name":"Riyan Parag","dismissal":"b Mohammed Shami","runs_scored":15,"balls_faced":15,"fours":1,"sixes":0,"strike_rate":100,"percent_runs":"11.54%","overs":null,"maidens":null,"runs_given":null,"wickets_taken":null,"economy":null,"percent_wickets":null,"catches":1,"opponent":"Gujarat Titans"},{"player_name":"Mohammed Shami","dismissal":null,"runs_scored":null,"balls_faced":null,"fours":null,"sixes":null,"strike_rate":null,"percent_runs":null,"overs":4,"maidens":0,"runs_given":33,"wickets_taken":1,"economy":8.25,"percent_wickets":10,"catches":1,"opponent":"Rajasthan Royals"},{"player_name":"Yash Dayal","dismissal":null,"runs_scored":null,"balls_faced":null,"fours":null,"sixes":null,"strike_rate":null,"percent_runs":null,"overs":3,"maidens":0,"runs_given":18,"wickets_taken":1,"economy":6,"percent_wickets":10,"catches":0,"opponent":"Rajasthan Royals"},{"player_name":"Lockie Ferguson","dismissal":null,"runs_scored":null,"balls_faced":null,"fours":null,"sixes":null,"strike_rate":null,"percent_runs":null,"overs":3,"maidens":0,"runs_given":22,"wickets_taken":0,"economy":7.33,"percent_wickets":null,"catches":0,"opponent":"Rajasthan Royals"},{"player_name":"Rashid Khan","dismissal":null,"runs_scored":null,"balls_faced":null,"fours":null,"sixes":null,"strike_rate":null,"percent_runs":null,"overs":4,"maidens":0,"runs_given":18,"wickets_taken":1,"economy":4.5,"percent_wickets":10,"catches":0,"opponent":"Rajasthan Royals"},{"player_name":"Sai Kishore","dismissal":null,"runs_scored":null,"balls_faced":null,"fours":null,"sixes":null,"strike_rate":null,"percent_runs":null,"overs":2,"maidens":0,"runs_given":20,"wickets_taken":2,"economy":10,"percent_wickets":20,"catches":2,"opponent":"Rajasthan Royals"},{"player_name":"Wriddhiman Saha","dismissal":"b Prasidh Krishna","runs_scored":5,"balls_faced":7,"fours":1,"sixes":0,"strike_rate":71.43,"percent_runs":"3.76%","overs":null,"maidens":null,"runs_given":null,"wickets_taken":null,"economy":null,"percent_wickets":null,"catches":1,"opponent":"Rajasthan Royals"},{"player_name":"Shubman Gill","dismissal":"not out","runs_scored":45,"balls_faced":43,"fours":3,"sixes":1,"strike_rate":104.65,"percent_runs":"33.83%","overs":null,"maidens":null,"runs_given":null,"wickets_taken":null,"economy":null,"percent_wickets":null,"catches":0,"opponent":"Rajasthan Royals"},{"player_name":"Matthew Wade","dismissal":"c Parag b Boult","runs_scored":8,"balls_faced":10,"fours":0,"sixes":1,"strike_rate":80,"percent_runs":"6.02%","overs":null,"maidens":null,"runs_given":null,"wickets_taken":null,"economy":null,"percent_wickets":null,"catches":0,"opponent":"Rajasthan Royals"},{"player_name":"Hardik Pandya","dismissal":"c Jaiswal b Chahal","runs_scored":34,"balls_faced":30,"fours":3,"sixes":1,"strike_rate":113.33,"percent_runs":"25.56%","overs":4,"maidens":0,"runs_given":17,"wickets_taken":3,"economy":4.25,"percent_wickets":30,"catches":0,"opponent":"Rajasthan Royals"},{"player_name":"David Miller","dismissal":"not out","runs_scored":32,"balls_faced":19,"fours":3,"sixes":1,"strike_rate":168.42,"percent_runs":"24.06%","overs":null,"maidens":null,"runs_given":null,"wickets_taken":null,"economy":null,"percent_wickets":null,"catches":1,"opponent":"Rajasthan Royals"},{"player_name":"Rahul Tewatia","dismissal":null,"runs_scored":null,"balls_faced":null,"fours":null,"sixes":null,"strike_rate":null,"percent_runs":null,"overs":null,"maidens":null,"runs_given":null,"wickets_taken":null,"economy":null,"percent_wickets":null,"catches":1,"opponent":"Rajasthan Royals"},{"player_name":"Trent Boult","dismissal":null,"runs_scored":null,"balls_faced":null,"fours":null,"sixes":null,"strike_rate":null,"percent_runs":null,"overs":4,"maidens":1,"runs_given":14,"wickets_taken":1,"economy":3.5,"percent_wickets":10,"catches":0,"opponent":"Gujarat Titans"},{"player_name":"Prasidh Krishna","dismissal":"not out","runs_scored":0,"balls_faced":0,"fours":0,"sixes":0,"strike_rate":0,"percent_runs":"","overs":4,"maidens":0,"runs_given":40,"wickets_taken":1,"economy":10,"percent_wickets":10,"catches":0,"opponent":"Gujarat Titans"},{"player_name":"Yuzvendra Chahal","dismissal":null,"runs_scored":null,"balls_faced":null,"fours":null,"sixes":null,"strike_rate":null,"percent_runs":null,"overs":4,"maidens":0,"runs_given":20,"wickets_taken":1,"economy":5,"percent_wickets":10,"catches":0,"opponent":"Gujarat Titans"},{"player_name":"Obed McCoy","dismissal":"run out","runs_scored":8,"balls_faced":5,"fours":0,"sixes":1,"strike_rate":160,"percent_runs":"6.15%","overs":3.1,"maidens":0,"runs_given":26,"wickets_taken":0,"economy":8.21,"percent_wickets":null,"catches":0,"opponent":"Gujarat Titans"},{"player_name":"Ravichandran Ashwin","dismissal":"c Miller b Kishore","runs_scored":6,"balls_faced":9,"fours":0,"sixes":0,"strike_rate":66.67,"percent_runs":"4.62%","overs":3,"maidens":0,"runs_given":32,"wickets_taken":0,"economy":10.67,"percent_wickets":null,"catches":0,"opponent":"Gujarat Titans"}]}