{"match_details":{"batting_first":"Royal Challengers Bangalore","batting_second":"Gujarat Titans","venue":"Brabourne Stadium, Mumbai","date":"30th April, 2022","winner":"Gujarat Titans"},"players":[{"player_name":"Virat Kohli","dismissal":"b Mohammed Shami","runs_scored":58,"balls_faced":53,"fours":6,"sixes":1,"strike_rate":109.43,"percent_runs":"34.12%","overs":null,"maidens":null,"runs_given":null,"wickets_taken":null,"economy":null,"percent_wickets":null,"catches":0,"opponent":"Gujarat Titans"},{"player_name":"Faf du Plessis","dismissal":"c †Saha b Sangwan","runs_scored":0,"balls_faced":4,"fours":0,"sixes":0,"strike_rate":0,"percent_runs":"","overs":null,"maidens":null,"runs_given":null,"wickets_taken":null,"economy":null,"percent_wickets":null,"catches":0,"opponent":"Gujarat Titans"},{"player_name":"Rajat Patidar","dismissal":"c Shubman Gill b Sangwan","runs_scored":52,"balls_faced":32,"fours":5,"sixes":2,"strike_rate":162.5,"percent_runs":"30.59%","overs":null,"maidens":null,"runs_given":null,"wickets_taken":null,"economy":null,"percent_wickets":null,"catches":1,"opponent":"Gujarat Titans"},{"player_name":"Dinesh Karthik","dismissal":"c Mohammed Shami b Rashid Khan","runs_scored":2,"balls_faced":3,"fours":0,"sixes":0,"strike_rate":66.67,"percent_runs":"1.18%","overs":null,"maidens":null,"runs_given":null,"wickets_taken":null,"economy":null,"percent_wickets":null,"catches":0,"opponent":"Gujarat Titans"},{"player_name":"Mahipal Lomror","dismissal":"c Miller b Joseph","runs_scored":16,"balls_faced":8,"fours":2,"sixes":1,"strike_rate":200,"percent_runs":"9.41%","overs":null,"maidens":null,"runs_given":null,"wickets_taken":null,"economy":null,"percent_wickets":null,"catches":1,"opponent":"Gujarat Titans"},{"player_name":"Mohammed Shami","dismissal":null,"runs_scored":null,"balls_faced":null,"fours":null,"sixes":null,"strike_rate":null,"percent_runs":null,"overs":4,"maidens":0,"runs_given":39,"wickets_taken":1,"economy":9.75,"percent_wickets":10,"catches":1,"opponent":"Royal Challengers Bangalore"},{"player_name":"Pradeep Sangwan","dismissal":null,"runs_scored":null,"balls_faced":null,"fours":null,"sixes":null,"strike_rate":null,"percent_runs":null,"overs":4,"maidens":0,"runs_given":19,"wickets_taken":2,"economy":4.75,"percent_wickets":20,"catches":0,"opponent":"Royal Challengers Bangalore"},{"player_name":"Alzarri Joseph","dismissal":null,"runs_scored":null,"balls_faced":null,"fours":null,"sixes":null,"strike_rate":null,"percent_runs":null,"overs":4,"maidens":0,"runs_given":42,"wickets_taken":1,"economy":10.5,"percent_wickets":10,"catches":0,"opponent":"Royal Challengers Bangalore"},{"player_name":"Rashid Khan","dismissal":null,"runs_scored":null,"balls_faced":null,"fours":null,"sixes":null,"strike_rate":null,"percent_runs":null,"overs":4,"maidens":0,"runs_given":29,"wickets_taken":1,"economy":7.25,"percent_wickets":10,"catches":1,"opponent":"Royal Challengers Bangalore"},{"player_name":"Lockie Ferguson","dismissal":null,"runs_scored":null,"balls_faced":null,"fours":null,"sixes":null,"strike_rate":null,"percent_runs":null,"overs":4,"maidens":0,"runs_given":36,"wickets_taken":1,"economy":9,"percent_wickets":10,"catches":0,"opponent":"Royal Challengers Bangalore"},{"player_name":"Wriddhiman Saha","dismissal":"c Patidar b Wanindu Hasaranga","runs_scored":29,"balls_faced":22,"fours":4,"sixes":0,"strike_rate":131.82,"percent_runs":"16.67%","overs":null,"maidens":null,"runs_given":null,"wickets_taken":null,"economy":null,"percent_wickets":null,"catches":1,"opponent":"Royal Challengers Bangalore"},{"player_name":"Shubman Gill","dismissal":"lbw b Shahbaz Ahmed","runs_scored":31,"balls_faced":28,"fours":3,"sixes":1,"strike_rate":110.71,"percent_runs":"17.82%","overs":null,"maidens":null,"runs_given":null,"wickets_taken":null,"economy":null,"percent_wickets":null,"catches":1,"opponent":"Royal Challengers Bangalore"},{"player_name":"Sai Sudharsan","dismissal":"c sub b Wanindu Hasaranga","runs_scored":20,"balls_faced":14,"fours":2,"sixes":0,"strike_rate":142.86,"percent_runs":"11.49%","overs":null,"maidens":null,"runs_given":null,"wickets_taken":null,"economy":null,"percent_wickets":null,"catches":0,"opponent":"Royal Challengers Bangalore"},{"player_name":"Hardik Pandya","dismissal":"c Lomror b Shahbaz Ahmed","runs_scored":3,"balls_faced":5,"fours":0,"sixes":0,"strike_rate":60,"percent_runs":"1.72%","overs":null,"maidens":null,"runs_given":null,"wickets_taken":null,"economy":null,"percent_wickets":null,"catches":0,"opponent":"Royal Challengers Bangalore"},{"player_name":"David Miller","dismissal":"not out","runs_scored":39,"balls_faced":24,"fours":4,"sixes":1,"strike_rate":162.5,"percent_runs":"22.41%","overs":null,"maidens":null,"runs_given":null,"wickets_taken":null,"economy":null,"percent_wickets":null,"catches":1,"opponent":"Royal Challengers Bangalore"},{"player_name":"Rahul Tewatia","dismissal":"not out","runs_scored":43,"balls_faced":25,"fours":5,"sixes":2,"strike_rate":172,"percent_runs":"24.71%","overs":null,"maidens":null,"runs_given":null,"wickets_taken":null,"economy":null,"percent_wickets":null,"catches":0,"opponent":"Royal Challengers Bangalore"},{"player_name":"Glenn Maxwell","dismissal":null,"runs_scored":null,"balls_faced":null,"fours":null,"sixes":null,"strike_rate":null,"percent_runs":null,"overs":1,"maidens":0,"runs_given":10,"wickets_taken":0,"economy":10,"percent_wickets":null,"catches":0,"opponent":"Gujarat Titans"},{"player_name":"Mohammed Siraj","dismissal":null,"runs_scored":null,"balls_faced":null,"fours":null,"sixes":null,"strike_rate":null,"percent_runs":null,"overs":4,"maidens":0,"runs_given":35,"wickets_taken":0,"economy":8.75,"percent_wickets":null,"catches":0,"opponent":"Gujarat Titans"},{"player_name":"Josh Hazlewood","dismissal":null,"runs_scored":null,"balls_faced":null,"fours":null,"sixes":null,"strike_rate":null,"percent_runs":null,"overs":3.3,"maidens":0,"runs_given":36,"wickets_taken":0,"economy":10.29,"percent_wickets":null,"catches":0,"opponent":"Gujarat Titans"},{"player_name":"Shahbaz Ahmed","dismissal":"not out","runs_scored":2,"balls_faced":2,"fours":0,"sixes":0,"strike_rate":100,"percent_runs":"1.18%","overs":3,"maidens":0,"runs_given":26,"wickets_taken":2,"economy":8.67,"percent_wickets":20,"catches":0,"opponent":"Gujarat Titans"},{"player_name":"Harshal Patel","dismissal":null,"runs_scored":null,"balls_faced":null,"fours":null,"sixes":null,"strike_rate":null,"percent_runs":null,"overs":4,"maidens":0,"runs_given":35,"wickets_taken":0,"economy":8.75,"percent_wickets":null,"catches":0,"opponent":"Gujarat Titans"},{"player_name":"Wanindu Hasaranga","dismissal":null,"runs_scored":null,"balls_faced":null,"fours":null,"sixes":null,"strike_rate":null,"percent_runs":null,"overs":4,"maidens":0,"runs_given":28,"wickets_taken":2,"economy":7,"percent_wickets":20,"catches":0,"opponent":"Gujarat Titans"}]}