{"match_details":{"batting_first":"Royal Challengers Bangalore","batting_second":"Mumbai Indians","venue":"M Chinnaswamy Stadium, Bengaluru, Bangalore","date":"11th May, 2016","winner":"Mumbai Indians"},"players":[{"player_name":"Virat Kohli","dismissal":"c Harbhajan Singh b McClenaghan","runs_scored":7,"balls_faced":7,"fours":0,"sixes":1,"strike_rate":100,"percent_runs":"4.64%","overs":null,"maidens":null,"runs_given":null,"wickets_taken":null,"economy":null,"percent_wickets":null,"catches":0,"opponent":"Mumbai Indians"},{"player_name":"Chris Gayle","dismissal":"c Sharma b Southee","runs_scored":5,"balls_faced":6,"fours":1,"sixes":0,"strike_rate":83.33,"percent_runs":"3.31%","overs":null,"maidens":null,"runs_given":null,"wickets_taken":null,"economy":null,"percent_wickets":null,"catches":0,"opponent":"Mumbai Indians"},{"player_name":"AB de Villiers","dismissal":"c Rayudu b Pandya","runs_scored":24,"balls_faced":27,"fours":1,"sixes":1,"strike_rate":88.89,"percent_runs":"15.89%","overs":null,"maidens":null,"runs_given":null,"wickets_taken":null,"economy":null,"percent_wickets":null,"catches":2,"opponent":"Mumbai Indians"},{"player_name":"KL Rahul","dismissal":"not out","runs_scored":68,"balls_faced":53,"fours":3,"sixes":4,"strike_rate":128.3,"percent_runs":"45.03%","overs":null,"maidens":null,"runs_given":null,"wickets_taken":null,"economy":null,"percent_wickets":null,"catches":0,"opponent":"Mumbai Indians"},{"player_name":"Sachin Baby","dismissal":"not out","runs_scored":25,"balls_faced":13,"fours":2,"sixes":2,"strike_rate":192.31,"percent_runs":"16.56%","overs":null,"maidens":null,"runs_given":null,"wickets_taken":null,"economy":null,"percent_wickets":null,"catches":0,"opponent":"Mumbai Indians"},{"player_name":"Tim Southee","dismissal":null,"runs_scored":null,"balls_faced":null,"fours":null,"sixes":null,"strike_rate":null,"percent_runs":null,"overs":4,"maidens":0,"runs_given":27,"wickets_taken":1,"economy":6.75,"percent_wickets":10,"catches":0,"opponent":"Royal Challengers Bangalore"},{"player_name":"Mitchell McClenaghan","dismissal":null,"runs_scored":null,"balls_faced":null,"fours":null,"sixes":null,"strike_rate":null,"percent_runs":null,"overs":4,"maidens":0,"runs_given":35,"wickets_taken":1,"economy":8.75,"percent_wickets":10,"catches":0,"opponent":"Royal Challengers Bangalore"},{"player_name":"Jasprit Bumrah","dismissal":null,"runs_scored":null,"balls_faced":null,"fours":null,"sixes":null,"strike_rate":null,"percent_runs":null,"overs":4,"maidens":0,"runs_given":28,"wickets_taken":0,"economy":7,"percent_wickets":null,"catches":0,"opponent":"Royal Challengers Bangalore"},{"player_name":"Krunal Pandya","dismissal":null,"runs_scored":null,"balls_faced":null,"fours":null,"sixes":null,"strike_rate":null,"percent_runs":null,"overs":4,"maidens":0,"runs_given":15,"wickets_taken":1,"economy":3.75,"percent_wickets":10,"catches":0,"opponent":"Royal Challengers Bangalore"},{"player_name":"Harbhajan Singh","dismissal":null,"runs_scored":null,"balls_faced":null,"fours":null,"sixes":null,"strike_rate":null,"percent_runs":null,"overs":3,"maidens":0,"runs_given":19,"wickets_taken":0,"economy":6.33,"percent_wickets":null,"catches":1,"opponent":"Royal Challengers Bangalore"},{"player_name":"Rohit Sharma","dismissal":"c de Villiers b Aaron","runs_scored":25,"balls_faced":24,"fours":3,"sixes":0,"strike_rate":104.17,"percent_runs":"16.34%","overs":null,"maidens":null,"runs_given":null,"wickets_taken":null,"economy":null,"percent_wickets":null,"catches":1,"opponent":"Royal Challengers Bangalore"},{"player_name":"Parthiv Patel","dismissal":"c Watson b Aravind","runs_scored":1,"balls_faced":2,"fours":0,"sixes":0,"strike_rate":50,"percent_runs":"0.65%","overs":null,"maidens":null,"runs_given":null,"wickets_taken":null,"economy":null,"percent_wickets":null,"catches":0,"opponent":"Royal Challengers Bangalore"},{"player_name":"Ambati Rayudu","dismissal":"c de Villiers b Aaron","runs_scored":44,"balls_faced":47,"fours":2,"sixes":2,"strike_rate":93.62,"percent_runs":"28.76%","overs":null,"maidens":null,"runs_given":null,"wickets_taken":null,"economy":null,"percent_wickets":null,"catches":1,"opponent":"Royal Challengers Bangalore"},{"player_name":"Nitish Rana","dismissal":"c Binny b Chahal","runs_scored":9,"balls_faced":11,"fours":0,"sixes":1,"strike_rate":81.82,"percent_runs":"5.88%","overs":null,"maidens":null,"runs_given":null,"wickets_taken":null,"economy":null,"percent_wickets":null,"catches":0,"opponent":"Royal Challengers Bangalore"},{"player_name":"Kieron Pollard","dismissal":"not out","runs_scored":35,"balls_faced":19,"fours":3,"sixes":2,"strike_rate":184.21,"percent_runs":"22.88%","overs":1,"maidens":0,"runs_given":22,"wickets_taken":0,"economy":22,"percent_wickets":null,"catches":0,"opponent":"Royal Challengers Bangalore"},{"player_name":"Jos Buttler","dismissal":"not out","runs_scored":29,"balls_faced":11,"fours":1,"sixes":3,"strike_rate":263.64,"percent_runs":"18.95%","overs":null,"maidens":null,"runs_given":null,"wickets_taken":null,"economy":null,"percent_wickets":null,"catches":0,"opponent":"Royal Challengers Bangalore"},{"player_name":"Stuart Binny","dismissal":null,"runs_scored":null,"balls_faced":null,"fours":null,"sixes":null,"strike_rate":null,"percent_runs":null,"overs":1,"maidens":0,"runs_given":2,"wickets_taken":0,"economy":2,"percent_wickets":null,"catches":1,"opponent":"Mumbai Indians"},{"player_name":"Sreenath Aravind","dismissal":null,"runs_scored":null,"balls_faced":null,"fours":null,"sixes":null,"strike_rate":null,"percent_runs":null,"overs":4,"maidens":0,"runs_given":23,"wickets_taken":1,"economy":5.75,"percent_wickets":10,"catches":0,"opponent":"Mumbai Indians"},{"player_name":"Chris Jordan","dismissal":null,"runs_scored":null,"balls_faced":null,"fours":null,"sixes":null,"strike_rate":null,"percent_runs":null,"overs":3,"maidens":0,"runs_given":37,"wickets_taken":0,"economy":12.33,"percent_wickets":null,"catches":0,"opponent":"Mumbai Indians"},{"player_name":"Shane Watson","dismissal":"run out","runs_scored":15,"balls_faced":14,"fours":1,"sixes":1,"strike_rate":107.14,"percent_runs":"9.93%","overs":3,"maidens":0,"runs_given":38,"wickets_taken":0,"economy":12.67,"percent_wickets":null,"catches":1,"opponent":"Mumbai Indians"},{"player_name":"Yuzvendra Chahal","dismissal":null,"runs_scored":null,"balls_faced":null,"fours":null,"sixes":null,"strike_rate":null,"percent_runs":null,"overs":4,"maidens":0,"runs_given":16,"wickets_taken":1,"economy":4,"percent_wickets":10,"catches":0,"opponent":"Mumbai Indians"},{"player_name":"Varun Aaron","dismissal":null,"runs_scored":null,"balls_faced":null,"fours":null,"sixes":null,"strike_rate":null,"percent_runs":null,"overs":3.4,"maidens":0,"runs_given":37,"wickets_taken":2,"economy":10.09,"percent_wickets":20,"catches":0,"opponent":"Mumbai Indians"}]}